scatlasvae/__init__.py
scatlasvae/_metadata.py
scatlasvae/_version.py
scatlasvae/data/__init__.py
scatlasvae/data/_dataloader.py
scatlasvae/externals/__init__.py
scatlasvae/externals/_trvae_mmd_loss.py
scatlasvae/externals/tabnet/__init__.py
scatlasvae/externals/tabnet/sparsemax.py
scatlasvae/externals/tabnet/tab_network.py
scatlasvae/externals/taming/__init__.py
scatlasvae/externals/taming/lr_scheduler.py
scatlasvae/externals/taming/util.py
scatlasvae/externals/taming/data/__init__.py
scatlasvae/externals/taming/data/ade20k.py
scatlasvae/externals/taming/data/annotated_objects_coco.py
scatlasvae/externals/taming/data/annotated_objects_dataset.py
scatlasvae/externals/taming/data/annotated_objects_open_images.py
scatlasvae/externals/taming/data/base.py
scatlasvae/externals/taming/data/coco.py
scatlasvae/externals/taming/data/custom.py
scatlasvae/externals/taming/data/faceshq.py
scatlasvae/externals/taming/data/helper_types.py
scatlasvae/externals/taming/data/image_transforms.py
scatlasvae/externals/taming/data/imagenet.py
scatlasvae/externals/taming/data/open_images_helper.py
scatlasvae/externals/taming/data/sflckr.py
scatlasvae/externals/taming/data/utils.py
scatlasvae/externals/taming/models/__init__.py
scatlasvae/externals/taming/models/cond_transformer.py
scatlasvae/externals/taming/models/dummy_cond_stage.py
scatlasvae/externals/taming/models/vqgan.py
scatlasvae/externals/taming/modules/__init__.py
scatlasvae/externals/taming/modules/util.py
scatlasvae/externals/taming/modules/diffusionmodules/__init__.py
scatlasvae/externals/taming/modules/diffusionmodules/model.py
scatlasvae/externals/taming/modules/discriminator/__init__.py
scatlasvae/externals/taming/modules/discriminator/model.py
scatlasvae/externals/taming/modules/losses/__init__.py
scatlasvae/externals/taming/modules/losses/lpips.py
scatlasvae/externals/taming/modules/losses/segmentation.py
scatlasvae/externals/taming/modules/losses/vqperceptual.py
scatlasvae/externals/taming/modules/misc/__init__.py
scAtlasVAE-1.0.5.9.dist-info/LICENSE
scAtlasVAE-1.0.5.9.dist-info/METADATA
scAtlasVAE-1.0.5.9.dist-info/WHEEL
scAtlasVAE-1.0.5.9.dist-info/dependency_links.txt
scAtlasVAE-1.0.5.9.dist-info/top_level.txt
scAtlasVAE-1.0.5.9.dist-info/RECORD
