Metadata-Version: 2.1
Name: scAtlasVAE
Version: 1.0.5.9
Summary: scAtlasVAE: a deep learning framework for atlas-scale scRNA-seq integration and analysis
Home-page: https://github.com/WanluLiuLab/scAtlasVAE
Download-URL: https://github.com/WanluLiuLab/scAtlasVAE
Author: Ziwei Xue
Author-email: xueziweisz@gmail.com
License-File: LICENSE
Requires-Dist: anndata ==0.8.0
Requires-Dist: numba ==0.57.1
Requires-Dist: numpy <1.22,>=1.21
Requires-Dist: scanpy ==1.8.1
Requires-Dist: scikit-learn ==0.24.1
Requires-Dist: matplotlib <=3.6.3,>=3.3.4
Requires-Dist: einops >=0.4.1
Requires-Dist: biopython ==1.79
Requires-Dist: seaborn ==0.12.2
Requires-Dist: scirpy ==0.10.1
Requires-Dist: pandas ==1.4.2
Requires-Dist: tabulate >=0.8.9
Requires-Dist: umap-learn ==0.5.1
Requires-Dist: torch ==1.13.1
Requires-Dist: torchvision ==0.14.1
Requires-Dist: torchaudio ==0.13.1
Requires-Dist: plotly >=5.10.0
Requires-Dist: anndata-tensorstore
Provides-Extra: gpu
Requires-Dist: pynvml ==11.5.0 ; extra == 'gpu'
Requires-Dist: nvidia-ml-py3 ==7.352.0 ; extra == 'gpu'
